MANIFEST.in
Pipfile
Pipfile.lock
README.md
setup.py
./LICENSE.txt
./README.md
./pypat/libpat/LICENSE
./pypat/libpat/README.md
pypat/__init__.py
pypat/_pypat.c
pypat.egg-info/PKG-INFO
pypat.egg-info/SOURCES.txt
pypat.egg-info/dependency_links.txt
pypat.egg-info/not-zip-safe
pypat.egg-info/top_level.txt
pypat/libpat/CMakeLists.txt
pypat/libpat/libpat/CMakeLists.txt
pypat/libpat/libpat/include/pat/pat.h
pypat/libpat/libpat/include/pat/pat_error.h
pypat/libpat/libpat/src/pat.c
pypat/libpat/libpat/src/pat_audio_device.c
pypat/libpat/libpat/src/pat_audio_device.h
pypat/libpat/libpat/src/pat_decode.c
pypat/libpat/libpat/src/pat_decode.h
pypat/libpat/libpat/src/pat_error.c
pypat/libpat/libpat/src/pat_ring_buffer.c
pypat/libpat/libpat/src/pat_ring_buffer.h
pypat/libpat/modules/FindFFmpeg.cmake
pypat/libpat/modules/FindSDL2.cmake
pypat/libpat/patplay/CMakeLists.txt
pypat/libpat/patplay/src/pat_play.c
test/test_pypat.py