Metadata-Version: 2.1
Name: pypat
Version: 0.6.0
Summary: A Python library that makes playing audio simple.
Home-page: https://github.com/tnewman/pat
Author: Thomas Newman
Author-email: tnewman@users.noreply.github.com
License: UNKNOWN
Platform: UNKNOWN
Classifier: Programming Language :: Python :: 3
Classifier: License :: OSI Approved :: GNU Lesser General Public License v2 or later (LGPLv2+)
Classifier: Operating System :: OS Independent
